setup.py
uwsgi_cli/__init__.py
uwsgi_cli/client.py
uwsgi_cli.egg-info/PKG-INFO
uwsgi_cli.egg-info/SOURCES.txt
uwsgi_cli.egg-info/dependency_links.txt
uwsgi_cli.egg-info/entry_points.txt
uwsgi_cli.egg-info/requires.txt
uwsgi_cli.egg-info/top_level.txt