Metadata-Version: 1.1
Name: uwsgi-cli
Version: 1.0
Summary: a simple uwsgi client
Home-page: http://xiaorui.cc
Author: ruifengyun
Author-email: rfyiamcool@163.com
License: MIT
Keywords: uwsgi,fengyun,ruifengyun
Platform: UNKNOWN
Classifier: Development Status :: 4 - Beta
Classifier: Intended Audience :: Developers
Classifier: License :: OSI Approved :: MIT License
Classifier: Programming Language :: Python :: 2.7
Classifier: Programming Language :: Python :: 3.0
Classifier: Topic :: Software Development :: Libraries :: Python Modules
